ament_cmake_python/_dummy.cpython-310-x86_64-linux-gnu.so
ros_ament_cmake_python-2.7.3.data/data/share/ament_cmake_python/local_setup.bash
ros_ament_cmake_python-2.7.3.data/data/share/ament_cmake_python/local_setup.dsv
ros_ament_cmake_python-2.7.3.data/data/share/ament_cmake_python/local_setup.sh
ros_ament_cmake_python-2.7.3.data/data/share/ament_cmake_python/local_setup.zsh
ros_ament_cmake_python-2.7.3.data/data/share/ament_cmake_python/package.dsv
ros_ament_cmake_python-2.7.3.data/data/share/ament_cmake_python/package.xml
ros_ament_cmake_python-2.7.3.data/data/share/ament_cmake_python/cmake/ament_cmake_python-extras.cmake
ros_ament_cmake_python-2.7.3.data/data/share/ament_cmake_python/cmake/ament_cmake_pythonConfig-version.cmake
ros_ament_cmake_python-2.7.3.data/data/share/ament_cmake_python/cmake/ament_cmake_pythonConfig.cmake
ros_ament_cmake_python-2.7.3.data/data/share/ament_cmake_python/cmake/ament_get_python_install_dir.cmake
ros_ament_cmake_python-2.7.3.data/data/share/ament_cmake_python/cmake/ament_python_install_module.cmake
ros_ament_cmake_python-2.7.3.data/data/share/ament_cmake_python/cmake/ament_python_install_package.cmake
ros_ament_cmake_python-2.7.3.data/data/share/ament_cmake_python/environment/ament_prefix_path.dsv
ros_ament_cmake_python-2.7.3.data/data/share/ament_cmake_python/environment/ament_prefix_path.sh
ros_ament_cmake_python-2.7.3.data/data/share/ament_cmake_python/environment/path.dsv
ros_ament_cmake_python-2.7.3.data/data/share/ament_cmake_python/environment/path.sh
ros_ament_cmake_python-2.7.3.data/data/share/ament_index/resource_index/package_run_dependencies/ament_cmake_python
ros_ament_cmake_python-2.7.3.data/data/share/ament_index/resource_index/packages/ament_cmake_python
ros_ament_cmake_python-2.7.3.data/data/share/ament_index/resource_index/parent_prefix_path/ament_cmake_python
ros_ament_cmake_python-2.7.3.dist-info/METADATA
ros_ament_cmake_python-2.7.3.dist-info/WHEEL
ros_ament_cmake_python-2.7.3.dist-info/top_level.txt
ros_ament_cmake_python-2.7.3.dist-info/RECORD
