Metadata-Version: 2.4
Name: ros-ament-cmake-python
Version: 2.7.3
Summary: A ROS package providing CMake functions to install Python packages and modules, simplifying Python integration in ROS builds.
Dynamic: description
Dynamic: description-content-type
Dynamic: summary
